mavdac-0.1.5.dist-info/METADATA
mavdac-0.1.5.dist-info/WHEEL
mavdac-0.1.5.dist-info/entry_points.txt
mavdac/__init__.py
mavdac/__main__.py
mavdac/display.py
mavdac/mavdac.pypy310-pp73-x86_64-linux-gnu.so
mavdac/py.typed
mavdac/util.py
mavdac-0.1.5.dist-info/RECORD
