Metadata-Version: 2.4
Name: mavdac
Version: 0.1.5
Classifier: Programming Language :: Rust
Classifier: Programming Language :: Python :: Implementation :: CPython
Classifier: Programming Language :: Python :: Implementation :: PyPy
Requires-Dist: numpy
Summary: MAVIS Differential Astrometric Calibrations
Author-email: Jesse Cranney <jesse.cranney@anu.edu.au>
Requires-Python: >=3.8
